on_done/__init__.py
on_done/_on_done.py
on_done-0.1.1.dist-info/LICENSE
on_done-0.1.1.dist-info/METADATA
on_done-0.1.1.dist-info/WHEEL
on_done-0.1.1.dist-info/top_level.txt
on_done-0.1.1.dist-info/RECORD
