Metadata-Version: 2.1
Name: on-done
Version: 0.1.1
Summary: IPython/Jupyter cell magic to execute code after a cell succeeds or fails
Home-page: https://github.com/parsiad/on-done
Author: Parsiad Azimzadeh
Author-email: parsiad.azimzadeh@gmail.com
Project-URL: Bug Tracker, https://github.com/parsiad/on-done/issues
Classifier: Programming Language :: Python :: 3
Classifier: License :: OSI Approved :: MIT License
Classifier: Operating System :: OS Independent
Requires-Python: >=3.6
License-File: LICENSE
Requires-Dist: ipython
